fado/__init__.py
fado/arguments/__init__.py
fado/arguments/arguments.py
fado/constants/__init__.py
fado/crypto/__init__.py
fado/crypto/certificate_generator.py
fado/data/__init__.py
fado/data/data_loader.py
fado/data/data_splitter.py
fado/docker/__init__.py
fado/docker/client/__init__.py
fado/docker/client/client_trainer.py
fado/docker/client/server_aggregator.py
fado/docker/client/torch_client.py
fado/docker/client/torch_server.py
fado/docker/client/utils.py
fado/docker/dev/__init__.py
fado/fedml_diff/__init__.py
fado/fedml_diff/core/__init__.py
fado/fedml_diff/core/distributed/__init__.py
fado/fedml_diff/core/distributed/fedml_comm_manager.py
fado/fedml_diff/core/distributed/communication/__init__.py
fado/fedml_diff/core/distributed/communication/grpc/__init__.py
fado/fedml_diff/core/distributed/communication/grpc/grpc_secure_comm_manager.py
fado/orchestrate/__init__.py
fado/orchestrate/orchestrator.py
FAaDO-0.0.2.dist-info/METADATA
FAaDO-0.0.2.dist-info/WHEEL
FAaDO-0.0.2.dist-info/top_level.txt
FAaDO-0.0.2.dist-info/RECORD
